hasattrs/__init__.py
hasattrs/attributes.py
hasattrs/checks.py
hasattrs/py.typed
hasattrs/types.py
hasattrs-0.1.0.dist-info/LICENSE.md
hasattrs-0.1.0.dist-info/METADATA
hasattrs-0.1.0.dist-info/WHEEL
hasattrs-0.1.0.dist-info/top_level.txt
hasattrs-0.1.0.dist-info/RECORD
